netbox_themes/__init__.py
netbox_themes/exceptions.py
netbox_themes/forms.py
netbox_themes/models.py
netbox_themes/navigation.py
netbox_themes/tables.py
netbox_themes/urls.py
netbox_themes/views.py
netbox_themes/api/__init__.py
netbox_themes/api/serializers.py
netbox_themes/migrations/0001_initial_netbox_themes.py
netbox_themes/migrations/0002_alter_theme_base_theme.py
netbox_themes/migrations/__init__.py
netbox_themes/templates/base/base.html
netbox_themes/templates/netbox_themes/theme.html
netbox_themes/templatetags/netbox_themes_template_filters.py
netbox_plugin_themes-0.5.1.dist-info/LICENSE
netbox_plugin_themes-0.5.1.dist-info/METADATA
netbox_plugin_themes-0.5.1.dist-info/WHEEL
netbox_plugin_themes-0.5.1.dist-info/top_level.txt
netbox_plugin_themes-0.5.1.dist-info/RECORD
