Metadata-Version: 2.2
Name: netbox-plugin-themes
Version: 0.5.1
Summary: A Netbox plugin to customise the look of Netbox using CSS themes
Author-email: Netbox Themes Plugin <null@example.com>
Project-URL: Homepage, https://github.com/rcrawf/netbox-plugin-themes
Project-URL: Issues, https://github.com/rcrawf/netbox-plugin-themes/issues
Classifier: Programming Language :: Python :: 3
Classifier: License :: OSI Approved :: MIT License
Classifier: Operating System :: OS Independent
Requires-Python: >=3.9
License-File: LICENSE
